mainmemory_<IMT2017022>.v
//This is the main memory ahere the data is stored.
//It takes the address from the alu and store or load according to the instruction opcode.

module mainmemory(address,clk,mem_read,mem_write,input_data,f_write,data);
input f_write;
integer f;
input [31:0] address,input_data;
input clk;
input [0:0] mem_read,mem_write;
output reg [31:0] data;
integer adr = 0;
reg [31:0] memory[100:0];

initial begin
     memory[0] =  32'b1001;
     memory[1] =  32'b1001;
     memory[2] =  32'b1001;
     memory[3] =  32'b1001;
     memory[4] =  32'b1001;
     memory[5] =  32'b1001;
     memory[6] =  32'b1001;
     memory[7] =  32'b1001;
     memory[8] =  32'b1001;
     memory[9] =  32'b1001;
     memory[10] =  32'b1001;
     memory[11] =  32'b1001;
     memory[12] =  32'b1001;
     memory[13] =  32'b1001;
     memory[14] =  32'b1001;
     memory[15] =  32'b1001;
     memory[16] =  32'b1001;
     memory[17] =  32'b1001;
     memory[18] =  32'b1001;
     memory[19] =  32'b1110;
     memory[20] =  32'b1111;
     memory[21] =  32'b1011;
end

always@(posedge clk) begin
    adr = address;
    if(mem_read == 1)        //Checking whether to store or load.
      data = memory[adr];
    else if(mem_write == 1)
    begin
      memory[adr] = input_data;
    end
  end

//Here we are doing the file handling.

always @ (posedge clk) begin
  if(f_write==1)
  begin
    f = $fopen("output_<IMT2017022>.txt","w");
    $fwrite(f,"%0d ", memory[50]);
    $fwrite(f,"%0d ", memory[51]);
    $fwrite(f,"%0d\n", memory[52]);
    $fwrite(f,"%0d ", memory[53]);
    $fwrite(f,"%0d ", memory[54]);
    $fwrite(f,"%0d\n", memory[55]);
    $fwrite(f,"%0d ", memory[56]);
    $fwrite(f,"%0d ", memory[57]);
    $fwrite(f,"%0d\n", memory[58]);
    $fclose(f);

  end
end
endmodule

ALU_<IMT2017022>.v
//This is the alu module that takes the alu control and gives the desire output.

module alu(in1,in2,clk,control,out);

input [31:0] in1,in2;
input clk;
input[3:0] control;
output reg [31:0] out;

always@(posedge clk)
  begin
    case(control)
      4'b0000 : out = (in1 & in2);   //AND
      4'b0001 : out = (in1 || in2);  //OR
      4'b0010 : out = in1 + in2;     //ADD
      4'b0011 : out = in1 - in2;     //SUB
      4'b0111 : out = in1*in2;       //MULT
      default : out  = 32'b000000;
    endcase
  end
endmodule

register_<IMT2017022>.v
//This is the register module which has 14 registers.
//s0 - s7
//t0 - t7 These are the temporary registers.

module register(inp,clk,ctrlunit,ctrl,out);

input [31:0]inp;
input [3:0] ctrl;
input clk;
input [8:0]ctrlunit;  //Ths will contain the control bits for instruction operations.
wire [31:0] temp;
output reg [31:0] out;
reg [31:0]reg_out1;
reg [31:0]reg_out2,reg_x;
reg f_write = 1'b0;

reg [31:0] s0 = 32'b0;
reg [31:0] s1 = 32'b0;
reg [31:0] s2 = 32'b0;
reg [31:0] s3 = 32'b0;
reg [31:0] s4 = 32'b0;
reg [31:0] s5 = 32'b0;
reg [31:0] s6 = 32'b0;
reg [31:0] s7 = 32'b0;

reg [31:0] t0 = 32'b0;
reg [31:0] t1 = 32'b0;
reg [31:0] t2 = 32'b0;
reg [31:0] t3 = 32'b0;
reg [31:0] t4 = 32'b0;
reg [31:0] t5 = 32'b0;
reg [31:0] t6 = 32'b0;
reg [31:0] t7 = 32'b0;

always @ (posedge clk) begin
  if(inp[31:26]==6'b111111) f_write = 1'b1;  //This is for the file handling.
end

//Checking the register and assigning the respected values as inputs.
always@(posedge clk)
  begin
      if(inp[25:21] == 5'b10000)reg_out1 = s0;
      if(inp[25:21] == 5'b10001)reg_out1 = s1;
      if(inp[25:21] == 5'b10010)reg_out1 = s2;
      if(inp[25:21] == 5'b10011)reg_out1 = s3;
      if(inp[25:21] == 5'b10100)reg_out1 = s4;
      if(inp[25:21] == 5'b10101)reg_out1 = s5;
      if(inp[25:21] == 5'b10110)reg_out1 = s6;
      if(inp[25:21] == 5'b10111)reg_out1 = s7;
      if(inp[25:21] == 5'b01000)reg_out1 = t0;
      if(inp[25:21] == 5'b01001)reg_out1 = t1;
      if(inp[25:21] == 5'b01010)reg_out1 = t2;
      if(inp[25:21] == 5'b01011)reg_out1 = t3;
      if(inp[25:21] == 5'b01100)reg_out1 = t4;
      if(inp[25:21] == 5'b01101)reg_out1 = t5;
      if(inp[25:21] == 5'b01110)reg_out1 = t6;
      if(inp[25:21] == 5'b01111)reg_out1 = t7;

      if(inp[20:16] == 5'b10000)reg_out2 = s0;
      if(inp[20:16] == 5'b10001)reg_out2 = s1;
      if(inp[20:16] == 5'b10010)reg_out2 = s2;
      if(inp[20:16] == 5'b10011)reg_out2 = s3;
      if(inp[20:16] == 5'b10100)reg_out2 = s4;
      if(inp[20:16] == 5'b10101)reg_out2 = s5;
      if(inp[20:16] == 5'b10110)reg_out2 = s6;
      if(inp[20:16] == 5'b10111)reg_out2 = s7;
      if(inp[20:16] == 5'b01000)reg_out2 = t0;
      if(inp[20:16] == 5'b01001)reg_out2 = t1;
      if(inp[20:16] == 5'b01010)reg_out2 = t2;
      if(inp[20:16] == 5'b01011)reg_out2 = t3;
      if(inp[20:16] == 5'b01100)reg_out2 = t4;
      if(inp[20:16] == 5'b01101)reg_out2 = t5;
      if(inp[20:16] == 5'b01110)reg_out2 = t6;
      if(inp[20:16] == 5'b01111)reg_out2 = t7;
  end

assign temp = reg_out2;
wire [31:0]alu_output,mem_out;

// in1 is from reg and in2 is from signed extension of input[16:0] for load and store instructions.

//Mux between registers and ALU which selects the second input gither from register or instruction depending on the opcode.
always@(posedge clk) begin
  case (ctrlunit[7])                        //ctrlunit[7:7] is the ALUSRC control bit to select the input.
    1'b0:reg_x = reg_out2;
    1'b1:reg_x = inp[15:0];
    default:reg_x = reg_out2 ;
    endcase
  end

alu u1(reg_out1,reg_x,clk,ctrl,alu_output);
mainmemory m1(alu_output,clk,ctrlunit[2],ctrlunit[6],temp,f_write,mem_out);

//Mux between the ALU and main memory.
always @ (posedge clk ) begin
  case (ctrlunit[3])
    1'b0:out = alu_output;
    1'b1:out = mem_out;
    default:out = out;
  endcase
end

reg [4:0] reg_dst;
always @ (posedge clk ) begin
  case (ctrlunit[0])
    1'b0:reg_dst = inp[20:16];
    1'b1:reg_dst = inp[15:11];
    default:reg_dst = inp[15:11];
  endcase
end


always @ (posedge clk) begin
  if(ctrlunit[8]==1)
  begin
  if(reg_dst == 5'b10000)s0 = out;
  if(reg_dst == 5'b10001)s1 = out;
  if(reg_dst == 5'b10010)s2 = out;
  if(reg_dst == 5'b10011)s3 = out;
  if(reg_dst == 5'b10100)s4 = out;
  if(reg_dst == 5'b10101)s5 = out;
  if(reg_dst == 5'b10110)s6 = out;
  if(reg_dst == 5'b10111)s7 = out;
  if(reg_dst == 5'b01000)t0 = out;
  if(reg_dst == 5'b01001)t1 = out;
  if(reg_dst == 5'b01010)t2 = out;
  if(reg_dst == 5'b01011)t3 = out;
  if(reg_dst == 5'b01100)t4 = out;
  if(reg_dst == 5'b01101)t5 = out;
  if(reg_dst == 5'b01110)t6 = out;
  if(reg_dst == 5'b01111)t7 = out;
  end
end

endmodule

alucontrol_<IMT2017022>.v
//This module generates the control signal for the alu.
//It takes aluop given by control unit and func as the input

module alucontrol(aluop,clk,func,cont);
input[1:0] aluop;
input clk;
input[5:0] func;
output reg [3:0] cont;

always@(posedge clk)
  begin
    if(aluop == 2'b00)                  //Load or Store
      cont = 4'b0010;
    else if(aluop == 2'b01)             //Beq
      cont = 4'b0011;
    else                                //R-type instruction
      begin
        if(func == 6'b100000)           //ADD
          cont = 4'b0010;
        else if(func == 6'b100010)      //SUB
          cont = 4'b0011;
        else if(func == 6'b110000)      //MULT
          cont = 4'b0111;
        else if(func == 6'b100100)      //AND
          cont = 4'b0000;
        else                            //OR
          cont = 4'b0001;
      end
  end
endmodule

instruction_set_<IMT2017022>.v
//This is the instruction set which takes the PC number and gives the instruction in that memory.

module instructionset(PC,clk,output_instruction);

input [31:0] PC;
output reg [31:0] output_instruction;
input clk;
reg [31:0] instruction[150:0];

integer num;

//These are the instructions that we use for matrix multiplication.

initial begin
    instruction[0] = 32'b10001110111100000000000000000000;
    instruction[1] = 32'b10001110111100010000000000001001;
    instruction[2] = 32'b00000010000100010100000000110000;
    instruction[3] = 32'b10001110111100000000000000000001;
    instruction[4] = 32'b10001110111100010000000000001100;
    instruction[5] = 32'b00000010000100010100100000110000;
    instruction[6] = 32'b10001110111100000000000000000010;
    instruction[7] = 32'b10001110111100010000000000001111;
    instruction[8] = 32'b00000010000100010101000000110000;
    instruction[9] = 32'b00000001000010010101100000100000;
    instruction[10] = 32'b00000001010010110110000000100000;
    instruction[11] = 32'b10101110111011000000000000110010;
// end
    instruction[12] = 32'b10001110111100000000000000000000;
    instruction[13] = 32'b10001110111100010000000000001010;
    instruction[14] = 32'b00000010000100010100000000110000;
    instruction[15] = 32'b10001110111100000000000000000001;
    instruction[16] = 32'b10001110111100010000000000001101;
    instruction[17] = 32'b00000010000100010100100000110000;
    instruction[18] = 32'b10001110111100000000000000000010;
    instruction[19] = 32'b10001110111100010000000000010000;
    instruction[20] = 32'b00000010000100010101000000110000;
    instruction[21] = 32'b00000001000010010101100000100000;
    instruction[22] = 32'b00000001010010110110000000100000;
    instruction[23] = 32'b10101110111011000000000000110011;
//end
    instruction[24] = 32'b10001110111100000000000000000000;
    instruction[25] = 32'b10001110111100010000000000001011;
    instruction[26] = 32'b00000010000100010100000000110000;
    instruction[27] = 32'b10001110111100000000000000000001;
    instruction[28] = 32'b10001110111100010000000000001110;
    instruction[29] = 32'b00000010000100010100100000110000;
    instruction[30] = 32'b10001110111100000000000000000010;
    instruction[31] = 32'b10001110111100010000000000010001;
    instruction[32] = 32'b00000010000100010101000000110000;
    instruction[33] = 32'b00000001000010010101100000100000;
    instruction[34] = 32'b00000001010010110110000000100000;
    instruction[35] = 32'b10101110111011000000000000110100;
//end
    instruction[36] = 32'b10001110111100000000000000000011;
    instruction[37] = 32'b10001110111100010000000000001001;
    instruction[38] = 32'b00000010000100010100000000110000;
    instruction[39] = 32'b10001110111100000000000000000100;
    instruction[40] = 32'b10001110111100010000000000001100;
    instruction[41] = 32'b00000010000100010100100000110000;
    instruction[42] = 32'b10001110111100000000000000000101;
    instruction[43] = 32'b10001110111100010000000000001111;
    instruction[44] = 32'b00000010000100010101000000110000;
    instruction[45] = 32'b00000001000010010101100000100000;
    instruction[46] = 32'b00000001010010110110000000100000;
    instruction[47] = 32'b10101110111011000000000000110101;
//end
    instruction[48] = 32'b10001110111100000000000000000011;
    instruction[49] = 32'b10001110111100010000000000001010;
    instruction[50] = 32'b00000010000100010100000000110000;
    instruction[51] = 32'b10001110111100000000000000000100;
    instruction[52] = 32'b10001110111100010000000000001101;
    instruction[53] = 32'b00000010000100010100100000110000;
    instruction[54] = 32'b10001110111100000000000000000101;
    instruction[55] = 32'b10001110111100010000000000010000;
    instruction[56] = 32'b00000010000100010101000000110000;
    instruction[57] = 32'b00000001000010010101100000100000;
    instruction[58] = 32'b00000001010010110110000000100000;
    instruction[59] = 32'b10101110111011000000000000110110;
//end
    instruction[60] = 32'b10001110111100000000000000000011;
    instruction[61] = 32'b10001110111100010000000000001011;
    instruction[62] = 32'b00000010000100010100000000110000;
    instruction[63] = 32'b10001110111100000000000000000100;
    instruction[64] = 32'b10001110111100010000000000001110;
    instruction[65] = 32'b00000010000100010100100000110000;
    instruction[66] = 32'b10001110111100000000000000000101;
    instruction[67] = 32'b10001110111100010000000000010001;
    instruction[68] = 32'b00000010000100010101000000110000;
    instruction[69] = 32'b00000001000010010101100000100000;
    instruction[70] = 32'b00000001010010110110000000100000;
    instruction[71] = 32'b10101110111011000000000000110111;
//end
    instruction[72] = 32'b10001110111100000000000000000110;
    instruction[73] = 32'b10001110111100010000000000001001;
    instruction[74] = 32'b00000010000100010100000000110000;
    instruction[75] = 32'b10001110111100000000000000000111;
    instruction[76] = 32'b10001110111100010000000000001100;
    instruction[77] = 32'b00000010000100010100100000110000;
    instruction[78] = 32'b10001110111100000000000000001000;
    instruction[79] = 32'b10001110111100010000000000001111;
    instruction[80] = 32'b00000010000100010101000000110000;
    instruction[81] = 32'b00000001000010010101100000100000;
    instruction[82] = 32'b00000001010010110110000000100000;
    instruction[83] = 32'b10101110111011000000000000111000;
//end
    instruction[84] = 32'b10001110111100000000000000000110;
    instruction[85] = 32'b10001110111100010000000000001010;
    instruction[86] = 32'b00000010000100010100000000110000;
    instruction[87] = 32'b10001110111100000000000000000111;
    instruction[88] = 32'b10001110111100010000000000001101;
    instruction[89] = 32'b00000010000100010100100000110000;
    instruction[90] = 32'b10001110111100000000000000001000;
    instruction[91] = 32'b10001110111100010000000000010000;
    instruction[92] = 32'b00000010000100010101000000110000;
    instruction[93] = 32'b00000001000010010101100000100000;
    instruction[94] = 32'b00000001010010110110000000100000;
    instruction[95] = 32'b10101110111011000000000000111001;
//end
    instruction[96] = 32'b10001110111100000000000000000110;
    instruction[97] = 32'b10001110111100010000000000001011;
    instruction[98] = 32'b00000010000100010100000000110000;
    instruction[99] = 32'b10001110111100000000000000000111;
    instruction[100] = 32'b10001110111100010000000000001110;
    instruction[101] = 32'b00000010000100010100100000110000;
    instruction[102] = 32'b10001110111100000000000000001000;
    instruction[103] = 32'b10001110111100010000000000010001;
    instruction[104] = 32'b00000010000100010101000000110000;
    instruction[105] = 32'b00000001000010010101100000100000;
    instruction[106] = 32'b00000001010010110110000000100000;
    instruction[107] = 32'b10101110111011000000000000111010;

//instruction for file_handling
    instruction[108] = 32'b11111111111111111111111111111111;

end

always@(posedge clk)
  begin
    num = PC;
    output_instruction = instruction[num];  //Here we are assigning the instruction present in the memory.
  end


endmodule

control_<IMT2017022>.v
//This is the main module where we are creating the control bits and calling the modules.

module main(PC,clk,out);
  input [31:0] PC;
  input clk;
  output [31:0] out;
  reg k = 0;
  reg [8:0] main_control;
  wire [5:0] in;
  wire [3:0] control;
  wire [31:0] inp;

//This is the control bits that the control unit is generating.

  /*main_control[0] = regdest
    main_control[1] = Branch equal
    main_control[2] = Mem read
    main_control[3] = Mem to reg
    main_control[4] = ALuop[0]
    main_control[5] = ALuop[1]
    main_control[6] = Memwrite
    main_control[7] = Alusrc
    main_control[8] = Reg write*/

instructionset k1(PC,clk,inp);    //Loading the instruction from instruction set.
assign in = inp[31:26];           //Opcode to get the control bits.

always@(posedge clk) begin
    main_control[0] = (~in[0])&(~in[1])&(~in[2])&(~in[3])&(~in[4])&(~in[5]);
    main_control[1] = (~in[0])&(~in[1])&(in[2])&(~in[3])&(~in[4])&(~in[5]);
    main_control[2] = (in[0])&(in[1])&(~in[2])&(~in[3])&(~in[4])&(in[5]);
    main_control[3] = (in[0])&(in[1])&(~in[2])&(~in[3])&(~in[4])&(in[5]);
    main_control[4] = (~in[0])&(~in[1])&(in[2])&(~in[3])&(~in[4])&(~in[5]);
    main_control[5] = (~in[0])&(~in[1])&(~in[2])&(~in[3])&(~in[4])&(~in[5]);
    main_control[6] = (in[0])&(in[1])&(~in[2])&(in[3])&(~in[4])&(in[5]);
    main_control[7] = (in[0])&(in[1])&(~in[2])&(~in[3])&(~in[4])&(in[5]) || (in[0])&(in[1])&(~in[2])&(in[3])&(~in[4])&(in[5]);
    main_control[8] = ((~in[0])&(~in[1])&(~in[2])&(~in[3])&(~in[4])&(~in[5]) || (in[0])&(in[1])&(~in[2])&(~in[3])&(~in[4])&(in[5]));
    k = 1;
    end

alucontrol m0(main_control[5:4],clk,inp[5:0],control);  //Here we are calling the alucontrol module whch generates the control for ALU.
register u0(inp,clk,main_control,control,out);          //This is to get the data from the register.
endmodule

main_tb_<IMT2017022>.v
//This is to test the code and to get the output.

module main_tb;
  reg [31:0] PC;
  reg clk;
  wire [31:0] out;

  main uut(
    .PC(PC),
    .out(out),
    .clk(clk)
    );

  initial begin
    $dumpfile("main_out_<IMT2017022>.vcd");
    $dumpvars(0,main_tb);
    clk = 1;
    PC = 32'b0;
    end

//Increasing the PC number for every 30 clock cycles.
always
  #30 PC += 32'b1;


//Here we are defining the clock.

  always
  #0.5 clk = ~clk;
  initial #3270 $stop;
endmodule

main_out_<IMT2017022>.vcd
$date
	Mon Nov 26 09:39:00 2018
$end
$version
	Icarus Verilog
$end
$timescale
	1s
$end
$scope module main_tb $end
$var wire 32 ! out [31:0] $end
$var reg 32 " PC [31:0] $end
$var reg 1 # clk $end
$scope module uut $end
$var wire 32 $ PC [31:0] $end
$var wire 1 # clk $end
$var wire 32 % out [31:0] $end
$var wire 32 & inp [31:0] $end
$var wire 6 ' in [5:0] $end
$var wire 4 ( control [3:0] $end
$var reg 1 ) k $end
$var reg 9 * main_control [8:0] $end
$scope module k1 $end
$var wire 32 + PC [31:0] $end
$var wire 1 # clk $end
$var reg 32 , output_instruction [31:0] $end
$var integer 32 - num [31:0] $end
$upscope $end
$scope module m0 $end
$var wire 2 . aluop [1:0] $end
$var wire 1 # clk $end
$var wire 6 / func [5:0] $end
$var reg 4 0 cont [3:0] $end
$upscope $end
$scope module u0 $end
$var wire 1 # clk $end
$var wire 4 1 ctrl [3:0] $end
$var wire 9 2 ctrlunit [8:0] $end
$var wire 32 3 inp [31:0] $end
$var wire 32 4 temp [31:0] $end
$var wire 32 5 mem_out [31:0] $end
$var wire 32 6 alu_output [31:0] $end
$var reg 1 7 f_write $end
$var reg 32 8 out [31:0] $end
$var reg 5 9 reg_dst [4:0] $end
$var reg 32 : reg_out1 [31:0] $end
$var reg 32 ; reg_out2 [31:0] $end
$var reg 32 < reg_x [31:0] $end
$var reg 32 = s0 [31:0] $end
$var reg 32 > s1 [31:0] $end
$var reg 32 ? s2 [31:0] $end
$var reg 32 @ s3 [31:0] $end
$var reg 32 A s4 [31:0] $end
$var reg 32 B s5 [31:0] $end
$var reg 32 C s6 [31:0] $end
$var reg 32 D s7 [31:0] $end
$var reg 32 E t0 [31:0] $end
$var reg 32 F t1 [31:0] $end
$var reg 32 G t2 [31:0] $end
$var reg 32 H t3 [31:0] $end
$var reg 32 I t4 [31:0] $end
$var reg 32 J t5 [31:0] $end
$var reg 32 K t6 [31:0] $end
$var reg 32 L t7 [31:0] $end
$scope module m1 $end
$var wire 1 # clk $end
$var wire 1 7 f_write $end
$var wire 32 M input_data [31:0] $end
$var wire 1 N mem_read $end
$var wire 1 O mem_write $end
$var wire 32 P address [31:0] $end
$var reg 32 Q data [31:0] $end
$var integer 32 R adr [31:0] $end
$var integer 32 S f [31:0] $end
$upscope $end
$scope module u1 $end
$var wire 1 # clk $end
$var wire 4 T control [3:0] $end
$var wire 32 U in1 [31:0] $end
$var wire 32 V in2 [31:0] $end
$var reg 32 W out [31:0] $end
$upscope $end
$upscope $end
$upscope $end
$upscope $end
$enddefinitions $end
#0
$dumpvars
b0 W
bx V
bx U
b1 T
bx S
bx R
bx Q
b0 P
xO
xN
bx M
b0 L
b0 K
b0 J
b0 I
b0 H
b0 G
b0 F
b0 E
b0 D
b0 C
b0 B
b0 A
b0 @
b0 ?
b0 >
b0 =
bx <
bx ;
bx :
bx 9
bx 8
07
b0 6
bx 5
bx 4
b10001110111100000000000000000000 3
bx 2
b1 1
b1 0
b0 /
bx .
b0 -
b10001110111100000000000000000000 ,
b0 +
bx *
1)
b1 (
b100011 '
b10001110111100000000000000000000 &
bx %
b0 $
1#
b0 "
bx !
$end
#1
0#
#2
0O
b0 .
1N
b110001100 *
b110001100 2
b0 9
b0 <
b0 V
b0 4
b0 M
b0 ;
b0 :
b0 U
b0x R
b0x 6
b0x P
b0x W
1#
#3
0#
#4
b10 (
b10 0
b10 1
b10 T
b0 6
b0 P
b0 W
b10000 9
1#
#5
0#
#6
b1001 =
b1001 !
b1001 %
b1001 8
b1001 5
b1001 Q
b0 R
1#
#7
0#
#8
b1001 4
b1001 M
b1001 ;
1#
#9
0#
#10
1#
#11
0#
#12
1#
#13
0#
#14
1#
#15
0#
#16
1#
#17
0#
#18
1#
#19
0#
#20
1#
#21
0#
#22
1#
#23
0#
#24
1#
#25
0#
#26
1#
#27
0#
#28
1#
#29
0#
#30
b1001 /
b1001 >
b10001 9
b1001 <
b1001 V
b0 4
b0 M
b0 ;
b10001110111100010000000000001001 &
b10001110111100010000000000001001 ,
b10001110111100010000000000001001 3
b1 -
1#
b1 "
b1 $
b1 +
#31
0#
#32
b1001 6
b1001 P
b1001 W
b1001 4
b1001 M
b1001 ;
1#
#33
0#
#34
b1001 R
1#
#35
0#
#36
1#
#37
0#
#38
1#
#39
0#
#40
1#
#41
0#
#42
1#
#43
0#
#44
1#
#45
0#
#46
1#
#47
0#
#48
1#
#49
0#
#50
1#
#51
0#
#52
1#
#53
0#
#54
1#
#55
0#
#56
1#
#57
0#
#58
1#
#59
0#
#60
b110000 /
b0 '
b10000100010100000000110000 &
b10000100010100000000110000 ,
b10000100010100000000110000 3
b10 -
1#
b10 "
b10 $
b10 +
#61
0#
#62
b10 .
0N
b100100001 *
b100100001 2
b100000000110000 <
b100000000110000 V
b1001 :
b1001 U
1#
#63
0#
#64
b111 (
b111 0
b111 1
b111 T
b10010 6
b10010 P
b10010 W
b1001 <
b1001 V
b1000 9
1#
#65
0#
#66
b1010001 E
b1010001 !
b1010001 %
b1010001 8
b1010001 R
b1010001 6
b1010001 P
b1010001 W
1#
#67
0#
#68
1#
#69
0#
#70
1#
#71
0#
#72
1#
#73
0#
#74
1#
#75
0#
#76
1#
#77
0#
#78
1#
#79
0#
#80
1#
#81
0#
#82
1#
#83
0#
#84
1#
#85
0#
#86
1#
#87
0#
#88
1#
#89
0#
#90
b1 /
b100011 '
b0 9
b0 :
b0 U
b10001110111100000000000000000001 &
b10001110111100000000000000000001 ,
b10001110111100000000000000000001 3
b11 -
1#
b11 "
b11 $
b11 +
#91
0#
#92
b0 .
1N
b1 (
b1 0
b1 1
b1 T
b0 6
b0 P
b0 W
b1 <
b1 V
b1001 !
b1001 %
b1001 8
b10000 9
b110001100 *
b110001100 2
1#
#93
0#
#94
b1 R
b1 6
b1 P
b1 W
b10 (
b10 0
b10 1
b10 T
1#
#95
0#
#96
1#
#97
0#
#98
1#
#99
0#
#100
1#
#101
0#
#102
1#
#103
0#
#104
1#
#105
0#
#106
1#
#107
0#
#108
1#
#109
0#
#110
1#
#111
0#
#112
1#
#113
0#
#114
1#
#115
0#
#116
1#
#117
0#
#118
1#
#119
0#
#120
b1100 /
b10001110111100010000000000001100 &
b10001110111100010000000000001100 ,
b10001110111100010000000000001100 3
b100 -
1#
b100 "
b100 $
b100 +
#121
0#
#122
b10001 9
b1100 <
b1100 V
1#
#123
0#
#124
b1100 6
b1100 P
b1100 W
1#
#125
0#
#126
b1100 R
1#
#127
0#
#128
1#
#129
0#
#130
1#
#131
0#
#132
1#
#133
0#
#134
1#
#135
0#
#136
1#
#137
0#
#138
1#
#139
0#
#140
1#
#141
0#
#142
1#
#143
0#
#144
1#
#145
0#
#146
1#
#147
0#
#148
1#
#149
0#
#150
b110000 /
b0 '
b100100000110000 <
b100100000110000 V
b1001 :
b1001 U
b10000100010100100000110000 &
b10000100010100100000110000 ,
b10000100010100100000110000 3
b101 -
1#
b101 "
b101 $
b101 +
#151
0#
#152
b10 .
0N
b10010 6
b10010 P
b10010 W
b1001 <
b1001 V
b1100 !
b1100 %
b1100 8
b1001 9
b100100001 *
b100100001 2
1#
#153
0#
#154
b1010001 F
b1010001 !
b1010001 %
b1010001 8
b1010001 R
b1010001 6
b1010001 P
b1010001 W
b111 (
b111 0
b111 1
b111 T
1#
#155
0#
#156
1#
#157
0#
#158
1#
#159
0#
#160
1#
#161
0#
#162
1#
#163
0#
#164
1#
#165
0#
#166
1#
#167
0#
#168
1#
#169
0#
#170
1#
#171
0#
#172
1#
#173
0#
#174
1#
#175
0#
#176
1#
#177
0#
#178
1#
#179
0#
#180
b10 /
b100011 '
b10001110111100000000000000000010 &
b10001110111100000000000000000010 ,
b10001110111100000000000000000010 3
b110 -
1#
b110 "
b110 $
b110 +
#181
0#
#182
b0 .
1N
b110001100 *
b110001100 2
b0 9
b1 !
b1 %
b1 8
b0 :
b0 U
b1 R
b1 6
b1 P
b1 W
b1 (
b1 0
b1 1
b1 T
1#
#183
0#
#184
b10 (
b10 0
b10 1
b10 T
b10 <
b10 V
b1001 !
b1001 %
b1001 8
b10000 9
1#
#185
0#
#186
b10 R
b10 6
b10 P
b10 W
1#
#187
0#
#188
1#
#189
0#
#190
1#
#191
0#
#192
1#
#193
0#
#194
1#
#195
0#
#196
1#
#197
0#
#198
1#
#199
0#
#200
1#
#201
0#
#202
1#
#203
0#
#204
1#
#205
0#
#206
1#
#207
0#
#208
1#
#209
0#
#210
b1111 /
b10001 9
b1111 <
b1111 V
b10001110111100010000000000001111 &
b10001110111100010000000000001111 ,
b10001110111100010000000000001111 3
b111 -
1#
b111 "
b111 $
b111 +
#211
0#
#212
b1111 6
b1111 P
b1111 W
1#
#213
0#
#214
b1111 R
1#
#215
0#
#216
1#
#217
0#
#218
1#
#219
0#
#220
1#
#221
0#
#222
1#
#223
0#
#224
1#
#225
0#
#226
1#
#227
0#
#228
1#
#229
0#
#230
1#
#231
0#
#232
1#
#233
0#
#234
1#
#235
0#
#236
1#
#237
0#
#238
1#
#239
0#
#240
b110000 /
b0 '
b10000100010101000000110000 &
b10000100010101000000110000 ,
b10000100010101000000110000 3
b1000 -
1#
b1000 "
b1000 $
b1000 +
#241
0#
#242
b10 .
0N
b100100001 *
b100100001 2
b101000000110000 <
b101000000110000 V
b1001 :
b1001 U
1#
#243
0#
#244
b111 (
b111 0
b111 1
b111 T
b10010 6
b10010 P
b10010 W
b1001 <
b1001 V
b1111 !
b1111 %
b1111 8
b1010 9
1#
#245
0#
#246
b1010001 G
b1010001 !
b1010001 %
b1010001 8
b1010001 R
b1010001 6
b1010001 P
b1010001 W
1#
#247
0#
#248
1#
#249
0#
#250
1#
#251
0#
#252
1#
#253
0#
#254
1#
#255
0#
#256
1#
#257
0#
#258
1#
#259
0#
#260
1#
#261
0#
#262
1#
#263
0#
#264
1#
#265
0#
#266
1#
#267
0#
#268
1#
#269
0#
#270
b100000 /
b1010001 H
b1011 9
b1010001 <
b1010001 V
b1010001 4
b1010001 M
b1010001 ;
b1010001 :
b1010001 U
b1000010010101100000100000 &
b1000010010101100000100000 ,
b1000010010101100000100000 3
b1001 -
1#
b1001 "
b1001 $
b1001 +
#271
0#
#272
b10 (
b10 0
b10 1
b10 T
b1100110100001 6
b1100110100001 P
b1100110100001 W
1#
#273
0#
#274
b10100010 H
b10100010 !
b10100010 %
b10100010 8
b10100010 R
b10100010 6
b10100010 P
b10100010 W
1#
#275
0#
#276
1#
#277
0#
#278
1#
#279
0#
#280
1#
#281
0#
#282
1#
#283
0#
#284
1#
#285
0#
#286
1#
#287
0#
#288
1#
#289
0#
#290
1#
#291
0#
#292
1#
#293
0#
#294
1#
#295
0#
#296
1#
#297
0#
#298
1#
#299
0#
#300
b1010010110110000000100000 &
b1010010110110000000100000 ,
b1010010110110000000100000 3
b1010 -
1#
b1010 "
b1010 $
b1010 +
#301
0#
#302
b10100010 I
b1100 9
b10100010 <
b10100010 V
b10100010 4
b10100010 M
b10100010 ;
1#
#303
0#
#304
b11110011 6
b11110011 P
b11110011 W
1#
#305
0#
#306
b11110011 I
b11110011 !
b11110011 %
b11110011 8
b11110011 R
1#
#307
0#
#308
1#
#309
0#
#310
1#
#311
0#
#312
1#
#313
0#
#314
1#
#315
0#
#316
1#
#317
0#
#318
1#
#319
0#
#320
1#
#321
0#
#322
1#
#323
0#
#324
1#
#325
0#
#326
1#
#327
0#
#328
1#
#329
0#
#330
b110010 /
b101011 '
b0 9
b11110011 <
b11110011 V
b11110011 4
b11110011 M
b11110011 ;
b0 :
b0 U
b10101110111011000000000000110010 &
b10101110111011000000000000110010 ,
b10101110111011000000000000110010 3
b1011 -
1#
b1011 "
b1011 $
b1011 +
#331
0#
#332
1O
b0 .
b1 (
b1 0
b1 1
b1 T
b110010 6
b110010 P
b110010 W
b110010 <
b110010 V
b1100 9
b11000000 *
b11000000 2
1#
#333
0#
#334
b110010 !
b110010 %
b110010 8
b110010 R
b10 (
b10 0
b10 1
b10 T
1#
#335
0#
#336
1#
#337
0#
#338
1#
#339
0#
#340
1#
#341
0#
#342
1#
#343
0#
#344
1#
#345
0#
#346
1#
#347
0#
#348
1#
#349
0#
#350
1#
#351
0#
#352
1#
#353
0#
#354
1#
#355
0#
#356
1#
#357
0#
#358
1#
#359
0#
#360
b0 /
b100011 '
b10001110111100000000000000000000 &
b10001110111100000000000000000000 ,
b10001110111100000000000000000000 3
b1100 -
1#
b1100 "
b1100 $
b1100 +
#361
0#
#362
0O
1N
b110001100 *
b110001100 2
b10000 9
b0 <
b0 V
b1001 4
b1001 M
b1001 ;
1#
#363
0#
#364
b0 6
b0 P
b0 W
b11110011 5
b11110011 Q
b110010 4
b110010 M
b110010 ;
b1001 !
b1001 %
b1001 8
b110010 =
1#
#365
0#
#366
b1001 =
b1001 5
b1001 Q
b0 R
1#
#367
0#
#368
b1001 4
b1001 M
b1001 ;
1#
#369
0#
#370
1#
#371
0#
#372
1#
#373
0#
#374
1#
#375
0#
#376
1#
#377
0#
#378
1#
#379
0#
#380
1#
#381
0#
#382
1#
#383
0#
#384
1#
#385
0#
#386
1#
#387
0#
#388
1#
#389
0#
#390
b1010 /
b10001 9
b1010 <
b1010 V
b10001110111100010000000000001010 &
b10001110111100010000000000001010 ,
b10001110111100010000000000001010 3
b1101 -
1#
b1101 "
b1101 $
b1101 +
#391
0#
#392
b1010 6
b1010 P
b1010 W
1#
#393
0#
#394
b1010 R
1#
#395
0#
#396
1#
#397
0#
#398
1#
#399
0#
#400
1#
#401
0#
#402
1#
#403
0#
#404
1#
#405
0#
#406
1#
#407
0#
#408
1#
#409
0#
#410
1#
#411
0#
#412
1#
#413
0#
